section_to_course/__init__.py
section_to_course/admin.py
section_to_course/apps.py
section_to_course/compat.py
section_to_course/models.py
section_to_course/utils.py
section_to_course/api/__init__.py
section_to_course/api/urls.py
section_to_course/api/views.py
section_to_course/management/__init__.py
section_to_course/management/commands/__init__.py
section_to_course/management/commands/section_to_course.py
section_to_course/migrations/0001_initial.py
section_to_course/migrations/0002_alter_sectiontocourselink_last_refresh.py
section_to_course/migrations/__init__.py
section_to_course/settings/__init__.py
section_to_course/settings/common.py
section_to_course/static/section_to_course/js/admin-tools.js
section_to_course-0.4.3.dist-info/LICENSE.txt
section_to_course-0.4.3.dist-info/METADATA
section_to_course-0.4.3.dist-info/WHEEL
section_to_course-0.4.3.dist-info/entry_points.txt
section_to_course-0.4.3.dist-info/top_level.txt
section_to_course-0.4.3.dist-info/RECORD
