Metadata-Version: 2.1
Name: section-to-course
Version: 0.4.3
Summary: Factors sections from Open edX courses into their own new course.
Home-page: https://github.com/open-craft/section-to-course
Author: OpenCraft
Author-email: help@opencraft.com
License: AGPL 3.0
Keywords: Python edx
Classifier: Development Status :: 3 - Alpha
Classifier: Framework :: Django
Classifier: Framework :: Django :: 3.2
Classifier: Intended Audience :: Developers
Classifier: License :: OSI Approved :: GNU Affero General Public License v3 or later (AGPLv3+)
Classifier: Natural Language :: English
Classifier: Programming Language :: Python :: 3
Classifier: Programming Language :: Python :: 3.8
Requires-Python: >=3.8
License-File: LICENSE.txt
Requires-Dist: django
Requires-Dist: django-model-utils
Requires-Dist: django-object-actions
Requires-Dist: djangorestframework
Requires-Dist: edx-django-utils
Requires-Dist: edx-opaque-keys
Requires-Dist: edx-organizations
